zsharp/__init__.py
zsharp/atomnumber.py
zsharp/calculus.py
zsharp/classes.py
zsharp/constants.py
zsharp/functions.py
zsharp/guis.py
zsharp/hybridEoS.py
zsharp/imagedata.py
zsharp/imageio.py
zsharp/imageread.py
zsharp/io.py
zsharp/misc.py
zsharp/numerical.py
zsharp/optimize.py
zsharp/roots1.py
zsharp/smooth.py
zsharp/thermodynamics.py
zsharp-0.3.dist-info/DESCRIPTION.rst
zsharp-0.3.dist-info/METADATA
zsharp-0.3.dist-info/RECORD
zsharp-0.3.dist-info/WHEEL
zsharp-0.3.dist-info/metadata.json
zsharp-0.3.dist-info/top_level.txt
