Metadata-Version: 2.0
Name: zsharp
Version: 0.3
Summary: Crapy code from Zhenjie
Home-page: UNKNOWN
Author: Zhenjie Yan
Author-email: zhenjie@mit.edu
License: UNKNOWN
Platform: UNKNOWN
